{
  "pikeman": {
    "id": "pikeman",
    "name": "Ополченец",
    "faction": "haven",
    "tier": 1,
    "attack": 4,
    "defense": 5,
    "damage": { "min": 1, "max": 3 },
    "health": 10,
    "speed": 5,
    "growth": 14,
    "cost": { "gold": 60 },
    "abilities": [],
    "upgradeTo": "halberdier"
  },
  "halberdier": {
    "id": "halberdier",
    "name": "Алебардщик",
    "faction": "haven",
    "tier": 1,
    "attack": 6,
    "defense": 7,
    "damage": { "min": 2, "max": 4 },
    "health": 15,
    "speed": 5,
    "growth": 14,
    "cost": { "gold": 120 },
    "abilities": []
  },
  "archer": {
    "id": "archer",
    "name": "Лучник",
    "faction": "haven",
    "tier": 2,
    "attack": 6,
    "defense": 3,
    "damage": { "min": 2, "max": 4 },
    "health": 10,
    "speed": 4,
    "growth": 9,
    "cost": { "gold": 100 },
    "abilities": ["shooter"],
    "upgradeTo": "sharpshooter"
  },
  "sharpshooter": {
    "id": "sharpshooter",
    "name": "Меткий стрелок",
    "faction": "haven",
    "tier": 2,
    "attack": 8,
    "defense": 5,
    "damage": { "min": 3, "max": 5 },
    "health": 15,
    "speed": 6,
    "growth": 9,
    "cost": { "gold": 200 },
    "abilities": ["shooter", "double_shot"]
  },
  "griffin": {
    "id": "griffin",
    "name": "Грифон",
    "faction": "haven",
    "tier": 3,
    "attack": 8,
    "defense": 8,
    "damage": { "min": 3, "max": 6 },
    "health": 25,
    "speed": 6,
    "growth": 6,
    "cost": { "gold": 200 },
    "abilities": ["flying", "unlimited_retaliation"]
  },
  "knight": {
    "id": "knight",
    "name": "Рыцарь",
    "faction": "haven",
    "tier": 4,
    "attack": 15,
    "defense": 15,
    "damage": { "min": 7, "max": 10 },
    "health": 50,
    "speed": 7,
    "growth": 4,
    "cost": { "gold": 500 },
    "abilities": ["charge"]
  },
  "angel": {
    "id": "angel",
    "name": "Ангел",
    "faction": "haven",
    "tier": 5,
    "attack": 20,
    "defense": 20,
    "damage": { "min": 15, "max": 25 },
    "health": 100,
    "speed": 12,
    "growth": 2,
    "cost": { "gold": 3000, "crystal": 1 },
    "abilities": ["flying", "morale_boost", "resurrect"]
  },
  "skeleton": {
    "id": "skeleton",
    "name": "Скелет",
    "faction": "necropolis",
    "tier": 1,
    "attack": 5,
    "defense": 4,
    "damage": { "min": 1, "max": 3 },
    "health": 8,
    "speed": 5,
    "growth": 14,
    "cost": { "gold": 60 },
    "abilities": ["undead"],
    "upgradeTo": "skeleton_warrior"
  },
  "skeleton_warrior": {
    "id": "skeleton_warrior",
    "name": "Скелет-воин",
    "faction": "necropolis",
    "tier": 1,
    "attack": 7,
    "defense": 6,
    "damage": { "min": 2, "max": 4 },
    "health": 12,
    "speed": 5,
    "growth": 14,
    "cost": { "gold": 120 },
    "abilities": ["undead"]
  },
  "zombie": {
    "id": "zombie",
    "name": "Зомби",
    "faction": "necropolis",
    "tier": 2,
    "attack": 5,
    "defense": 5,
    "damage": { "min": 2, "max": 3 },
    "health": 20,
    "speed": 3,
    "growth": 8,
    "cost": { "gold": 100 },
    "abilities": ["undead", "disease"]
  },
  "vampire": {
    "id": "vampire",
    "name": "Вампир",
    "faction": "necropolis",
    "tier": 3,
    "attack": 10,
    "defense": 9,
    "damage": { "min": 4, "max": 6 },
    "health": 30,
    "speed": 6,
    "growth": 5,
    "cost": { "gold": 360 },
    "abilities": ["flying", "undead", "life_drain", "no_retaliation"]
  },
  "lich": {
    "id": "lich",
    "name": "Лич",
    "faction": "necropolis",
    "tier": 4,
    "attack": 13,
    "defense": 10,
    "damage": { "min": 7, "max": 10 },
    "health": 40,
    "speed": 7,
    "growth": 4,
    "cost": { "gold": 550 },
    "abilities": ["undead", "shooter", "death_cloud"]
  },
  "bone_dragon": {
    "id": "bone_dragon",
    "name": "Костяной дракон",
    "faction": "necropolis",
    "tier": 5,
    "attack": 18,
    "defense": 18,
    "damage": { "min": 15, "max": 25 },
    "health": 150,
    "speed": 9,
    "growth": 2,
    "cost": { "gold": 1800, "mercury": 1 },
    "abilities": ["flying", "undead", "morale_debuff", "aging"]
  },
  "wolf": {
    "id": "wolf",
    "name": "Волк",
    "faction": "preserve",
    "tier": 1,
    "attack": 5,
    "defense": 3,
    "damage": { "min": 2, "max": 4 },
    "health": 12,
    "speed": 7,
    "growth": 10,
    "cost": { "gold": 70 },
    "abilities": ["double_attack"]
  },
  "elf": {
    "id": "elf",
    "name": "Эльф",
    "faction": "preserve",
    "tier": 2,
    "attack": 7,
    "defense": 4,
    "damage": { "min": 3, "max": 5 },
    "health": 12,
    "speed": 6,
    "growth": 8,
    "cost": { "gold": 150 },
    "abilities": ["shooter", "double_shot"]
  },
  "unicorn": {
    "id": "unicorn",
    "name": "Единорог",
    "faction": "preserve",
    "tier": 3,
    "attack": 11,
    "defense": 9,
    "damage": { "min": 5, "max": 8 },
    "health": 40,
    "speed": 7,
    "growth": 5,
    "cost": { "gold": 400 },
    "abilities": ["blind_attack"]
  },
  "goblin": {
    "id": "goblin",
    "name": "Гоблин",
    "faction": "asylum",
    "tier": 1,
    "attack": 4,
    "defense": 2,
    "damage": { "min": 1, "max": 2 },
    "health": 8,
    "speed": 6,
    "growth": 16,
    "cost": { "gold": 40 },
    "abilities": []
  },
  "orc": {
    "id": "orc",
    "name": "Орк",
    "faction": "asylum",
    "tier": 2,
    "attack": 7,
    "defense": 5,
    "damage": { "min": 3, "max": 5 },
    "health": 15,
    "speed": 4,
    "growth": 8,
    "cost": { "gold": 120 },
    "abilities": ["shooter"]
  },
  "ogre": {
    "id": "ogre",
    "name": "Огр",
    "faction": "asylum",
    "tier": 3,
    "attack": 13,
    "defense": 7,
    "damage": { "min": 6, "max": 12 },
    "health": 40,
    "speed": 4,
    "growth": 4,
    "cost": { "gold": 350 },
    "abilities": []
  },
  "golem": {
    "id": "golem",
    "name": "Каменный голем",
    "faction": "academy",
    "tier": 1,
    "attack": 7,
    "defense": 10,
    "damage": { "min": 3, "max": 5 },
    "health": 25,
    "speed": 4,
    "growth": 8,
    "cost": { "gold": 150 },
    "abilities": ["damage_reduction", "magic_immunity"]
  },
  "mage": {
    "id": "mage",
    "name": "Маг",
    "faction": "academy",
    "tier": 2,
    "attack": 11,
    "defense": 8,
    "damage": { "min": 4, "max": 6 },
    "health": 20,
    "speed": 5,
    "growth": 6,
    "cost": { "gold": 250 },
    "abilities": ["shooter", "no_retaliation", "random_spell"]
  },
  "genie": {
    "id": "genie",
    "name": "Джинн",
    "faction": "academy",
    "tier": 3,
    "attack": 12,
    "defense": 12,
    "damage": { "min": 6, "max": 10 },
    "health": 40,
    "speed": 7,
    "growth": 4,
    "cost": { "gold": 400 },
    "abilities": ["flying", "random_spell", "hate_black_dragon"]
  }
}
